README.md
setup.py
cryptotik/__init__.py
cryptotik/binance.py
cryptotik/bitkonan.py
cryptotik/bitmex.py
cryptotik/bitstamp.py
cryptotik/bittrex.py
cryptotik/coinmarketcap.py
cryptotik/coinpaprika.py
cryptotik/common.py
cryptotik/cryptopia.py
cryptotik/exceptions.py
cryptotik/hitbtc.py
cryptotik/kraken.py
cryptotik/livecoin.py
cryptotik/poloniex.py
cryptotik/therock.py
cryptotik.egg-info/PKG-INFO
cryptotik.egg-info/SOURCES.txt
cryptotik.egg-info/dependency_links.txt
cryptotik.egg-info/requires.txt
cryptotik.egg-info/top_level.txt