Metadata-Version: 2.1
Name: cryptotik
Version: 0.36
Summary: Standardized common API for several cryptocurrency exchanges.
Home-page: https://github.com/indiciumfund/cryptotik
Author: Peerchemist
Author-email: peerchemist@protonmail.ch
License: BSD-3
Platform: UNKNOWN
